linksocks/__init__.py
linksocks/_base.py
linksocks/_cli.py
linksocks/_client.py
linksocks/_logging_config.py
linksocks/_server.py
linksocks/_utils.py
linksockslib/__init__.py
linksockslib/_linksockslib.cp311-win_amd64.h
linksockslib/_linksockslib.cp311-win_amd64.pyd
linksockslib/build.py
linksockslib/go.py
linksockslib/linksocks.py
linksockslib/linksockslib.c
linksockslib/linksockslib.go
linksockslib/linksockslib_go.h
linksocks-3.0.13.dist-info/METADATA
linksocks-3.0.13.dist-info/WHEEL
linksocks-3.0.13.dist-info/entry_points.txt
linksocks-3.0.13.dist-info/top_level.txt
linksocks-3.0.13.dist-info/RECORD
